<?xml version="1.0" encoding="utf-8" ?><dwsync><file name="contact-widgets-da_DK.mo" server="insight.pixelplaycreative.com//insight.pixelplaycreative.com/" local="3589036320" remote="3589036320" Dst="-1" /><file name="contact-widgets-de_DE.mo" server="insight.pixelplaycreative.com//insight.pixelplaycreative.com/" local="3589036320" remote="3589036320" Dst="-1" /><file name="contact-widgets-el.mo" server="insight.pixelplaycreative.com//insight.pixelplaycreative.com/" local="3589036320" remote="3589036320" Dst="-1" /><file name="contact-widgets-es_ES.mo" server="insight.pixelplaycreative.com//insight.pixelplaycreative.com/" local="3589036320" remote="3589036320" Dst="-1" /><file name="contact-widgets-es_MX.mo" server="insight.pixelplaycreative.com//insight.pixelplaycreative.com/" local="3589036320" remote="3589036320" Dst="-1" /><file name="contact-widgets-fi.mo" server="insight.pixelplaycreative.com//insight.pixelplaycreative.com/" local="3589036320" remote="3589036320" Dst="-1" /><file name="contact-widgets-fr_FR.mo" server="insight.pixelplaycreative.com//insight.pixelplaycreative.com/" local="3589036320" remote="3589036320" Dst="-1" /><file name="contact-widgets-hi_IN.mo" server="insight.pixelplaycreative.com//insight.pixelplaycreative.com/" local="3589036320" remote="3589036320" Dst="-1" /><file name="contact-widgets-id_ID.mo" server="insight.pixelplaycreative.com//insight.pixelplaycreative.com/" local="3589036320" remote="3589036320" Dst="-1" /><file name="contact-widgets-it_IT.mo" server="insight.pixelplaycreative.com//insight.pixelplaycreative.com/" local="3589036320" remote="3589036320" Dst="-1" /><file name="contact-widgets-ja.mo" server="insight.pixelplaycreative.com//insight.pixelplaycreative.com/" local="3589036320" remote="3589036320" Dst="-1" /><file name="contact-widgets-ko_KR.mo" server="insight.pixelplaycreative.com//insight.pixelplaycreative.com/" local="3589036320" remote="3589036320" Dst="-1" /><file name="contact-widgets-mr.mo" server="insight.pixelplaycreative.com//insight.pixelplaycreative.com/" local="3589036320" remote="3589036320" Dst="-1" /><file name="contact-widgets-ms_MY.mo" server="insight.pixelplaycreative.com//insight.pixelplaycreative.com/" local="3589036320" remote="3589036320" Dst="-1" /><file name="contact-widgets-nb_NO.mo" server="insight.pixelplaycreative.com//insight.pixelplaycreative.com/" local="3589036320" remote="3589036320" Dst="-1" /><file name="contact-widgets-nl_NL.mo" server="insight.pixelplaycreative.com//insight.pixelplaycreative.com/" local="3589036320" remote="3589036320" Dst="-1" /><file name="contact-widgets-pl_PL.mo" server="insight.pixelplaycreative.com//insight.pixelplaycreative.com/" local="3589036320" remote="3589036320" Dst="-1" /><file name="contact-widgets-pt_BR.mo" server="insight.pixelplaycreative.com//insight.pixelplaycreative.com/" local="3589036320" remote="3589036320" Dst="-1" /><file name="contact-widgets-pt_PT.mo" server="insight.pixelplaycreative.com//insight.pixelplaycreative.com/" local="3589036320" remote="3589036320" Dst="-1" /><file name="contact-widgets-ru_RU.mo" server="insight.pixelplaycreative.com//insight.pixelplaycreative.com/" local="3589036320" remote="3589036320" Dst="-1" /><file name="contact-widgets-sv_SE.mo" server="insight.pixelplaycreative.com//insight.pixelplaycreative.com/" local="3589036320" remote="3589036320" Dst="-1" /><file name="contact-widgets-th.mo" server="insight.pixelplaycreative.com//insight.pixelplaycreative.com/" local="3589036320" remote="3589036320" Dst="-1" /><file name="contact-widgets-tl.mo" server="insight.pixelplaycreative.com//insight.pixelplaycreative.com/" local="3589036320" remote="3589036320" Dst="-1" /><file name="contact-widgets-tr_TR.mo" server="insight.pixelplaycreative.com//insight.pixelplaycreative.com/" local="3589036320" remote="3589036320" Dst="-1" /><file name="contact-widgets-uk.mo" server="insight.pixelplaycreative.com//insight.pixelplaycreative.com/" local="3589036320" remote="3589036320" Dst="-1" /><file name="contact-widgets-vi.mo" server="insight.pixelplaycreative.com//insight.pixelplaycreative.com/" local="3589036320" remote="3589036320" Dst="-1" /><file name="contact-widgets-zh_CN.mo" server="insight.pixelplaycreative.com//insight.pixelplaycreative.com/" local="3589036320" remote="3589036320" Dst="-1" /><file name="contact-widgets-zh_HK.mo" server="insight.pixelplaycreative.com//insight.pixelplaycreative.com/" local="3589036320" remote="3589036320" Dst="-1" /><file name="contact-widgets-zh_TW.mo" server="insight.pixelplaycreative.com//insight.pixelplaycreative.com/" local="3589036320" remote="3589036320" Dst="-1" /><file name="contact-widgets.pot" server="insight.pixelplaycreative.com//insight.pixelplaycreative.com/" local="3589036320" remote="3589036320" Dst="-1" /></dwsync>